Metadata-Version: 2.1
Name: ezazure
Version: 0.0.9
Summary: easy azure interface for uploading & downloading files
Author: Mike Powell PhD
Author-email: mike@lakeslegendaries.com
License: MIT License
Platform: UNKNOWN
Requires-Python: >=3.7
License-File: LICENSE
